<?xml version="1.0" encoding="UTF-8"?>
<!DOCTYPE mapper PUBLIC "-//mybatis.org//DTD Mapper 3.0//EN" "http://mybatis.org/dtd/mybatis-3-mapper.dtd">
<mapper namespace="yu.seimonassistant.mapper.ReserveMapper">
  <resultMap id="BaseResultMap" type="yu.seimonassistant.entity.Reserve">
    <!-- @mbg.generated: generated automatically, do not modify! -->
    <id column="id" jdbcType="VARCHAR" property="id" />
    <result column="title" jdbcType="VARCHAR" property="title" />
    <result column="date" jdbcType="TIMESTAMP" property="date" />
    <result column="start_time" jdbcType="TIMESTAMP" property="startTime" />
    <result column="end_time" jdbcType="TIMESTAMP" property="endTime" />
    <result column="memo" jdbcType="LONGVARCHAR" property="memo" />
  </resultMap>
  <delete id="deleteByPrimaryKey" parameterType="java.lang.String">
    <!-- @mbg.generated: generated automatically, do not modify! -->
    delete from reserve
    where id = #{id,jdbcType=VARCHAR}
  </delete>
  <insert id="insert" keyColumn="id" keyProperty="id" parameterType="yu.seimonassistant.entity.Reserve" useGeneratedKeys="true">
    <!-- @mbg.generated: generated automatically, do not modify! -->
    insert into reserve (title, `date`, start_time, 
      end_time, memo)
    values (#{title,jdbcType=VARCHAR}, #{date,jdbcType=TIMESTAMP}, #{startTime,jdbcType=TIMESTAMP}, 
      #{endTime,jdbcType=TIMESTAMP}, #{memo,jdbcType=LONGVARCHAR})
  </insert>
  <update id="updateByPrimaryKey" parameterType="yu.seimonassistant.entity.Reserve">
    <!-- @mbg.generated: generated automatically, do not modify! -->
    update reserve
    set title = #{title,jdbcType=VARCHAR},
      `date` = #{date,jdbcType=TIMESTAMP},
      start_time = #{startTime,jdbcType=TIMESTAMP},
      end_time = #{endTime,jdbcType=TIMESTAMP},
      memo = #{memo,jdbcType=LONGVARCHAR}
    where id = #{id,jdbcType=VARCHAR}
  </update>
  <select id="selectByPrimaryKey" parameterType="java.lang.String" resultMap="BaseResultMap">
    <!-- @mbg.generated: generated automatically, do not modify! -->
    select id, title, `date`, start_time, end_time, memo
    from reserve
    where id = #{id,jdbcType=VARCHAR}
  </select>
  <select id="selectAll" resultMap="BaseResultMap">
    <!-- @mbg.generated: generated automatically, do not modify! -->
    select id, title, `date`, start_time, end_time, memo
    from reserve
  </select>
</mapper>